nextepoch/__init__.py
nextepoch/myco.py
nextepoch/py.typed
nextepoch-0.1.2.dist-info/METADATA
nextepoch-0.1.2.dist-info/WHEEL
nextepoch-0.1.2.dist-info/licenses/LICENSE
nextepoch-0.1.2.dist-info/RECORD
